FeishuGPT
