Metadata-Version: 2.1
Name: FeishuGPT
Version: 0.2.2
Summary: 通过飞书机器人使用 ChatGPT
Home-page: https://github.com/jtc1246/FeishuGPT
Author: Tiancheng Jiao
Author-email: jtc1246@outlook.com
License: GPL-2.0 License
Platform: all
Requires-Python: >=3
